writeLog/__init__.py
writeLog/writeLog.py
writeLog-0.0.8.dist-info/DESCRIPTION.rst
writeLog-0.0.8.dist-info/METADATA
writeLog-0.0.8.dist-info/RECORD
writeLog-0.0.8.dist-info/WHEEL
writeLog-0.0.8.dist-info/metadata.json
writeLog-0.0.8.dist-info/top_level.txt
