Metadata-Version: 2.0
Name: writeLog
Version: 0.0.8
Summary: A log writer function for py based docker containers.
Home-page: UNKNOWN
Author: Jacob Stewart
Author-email: jick.68.0@gmail.com
License: MIT
Keywords: logger
Platform: UNKNOWN
Requires-Python: ~=3.6
